{
    "created_time": "2019-06-23T06:03:38Z",
    "files": [
        {
            "attachment_folder": "",
            "attachments": [
            ],
            "created_time": "2018-11-18T03:25:09Z",
            "modified_time": "2018-11-18T03:43:09Z",
            "name": "20190625-关于小学期招新会议记录.md",
            "tags": [
            ]
        },
        {
            "attachment_folder": "",
            "attachments": [
            ],
            "created_time": "2018-11-18T03:25:09Z",
            "modified_time": "2018-11-18T03:43:09Z",
            "name": "20190627.md",
            "tags": [
            ]
        },
        {
            "attachment_folder": "",
            "attachments": [
            ],
            "created_time": "2018-11-18T03:25:09Z",
            "modified_time": "2018-11-18T03:43:09Z",
            "name": "20190630.md",
            "tags": [
            ]
        },
        {
            "attachment_folder": "",
            "attachments": [
            ],
            "created_time": "2018-11-18T03:25:09Z",
            "modified_time": "2018-11-18T03:43:09Z",
            "name": "20190707.md",
            "tags": [
            ]
        },
        {
            "attachment_folder": "",
            "attachments": [
            ],
            "created_time": "2018-11-18T03:25:09Z",
            "modified_time": "2018-11-18T03:43:09Z",
            "name": "20190714.md",
            "tags": [
            ]
        },
        {
            "attachment_folder": "",
            "attachments": [
            ],
            "created_time": "2018-11-18T03:25:09Z",
            "modified_time": "2018-11-18T03:43:09Z",
            "name": "20190901.md",
            "tags": [
            ]
        },
        {
            "attachment_folder": "",
            "attachments": [
            ],
            "created_time": "2018-11-18T03:25:09Z",
            "modified_time": "2018-11-18T03:43:09Z",
            "name": "20190906.md",
            "tags": [
            ]
        },
        {
            "attachment_folder": "",
            "attachments": [
            ],
            "created_time": "2018-11-18T03:25:09Z",
            "modified_time": "2018-11-18T03:43:09Z",
            "name": "20190922.md",
            "tags": [
            ]
        },
        {
            "attachment_folder": "",
            "attachments": [
            ],
            "created_time": "2018-11-18T03:25:09Z",
            "modified_time": "2018-11-18T03:43:09Z",
            "name": "20190925.md",
            "tags": [
            ]
        },
        {
            "attachment_folder": "",
            "attachments": [
            ],
            "created_time": "2018-11-18T03:25:09Z",
            "modified_time": "2018-11-18T03:43:09Z",
            "name": "20190929.md",
            "tags": [
            ]
        }
    ],
    "sub_directories": [
    ],
    "version": "1"
}